hcp_utils/__init__.py
hcp_utils/hcp_utils.py
hcp_utils/data/S1200.L.flat.32k_fs_LR.surf.gii
hcp_utils/data/S1200.L.inflated_MSMAll.32k_fs_LR.surf.gii
hcp_utils/data/S1200.L.midthickness_MSMAll.32k_fs_LR.surf.gii
hcp_utils/data/S1200.L.pial_MSMAll.32k_fs_LR.surf.gii
hcp_utils/data/S1200.L.sphere.32k_fs_LR.surf.gii
hcp_utils/data/S1200.L.very_inflated_MSMAll.32k_fs_LR.surf.gii
hcp_utils/data/S1200.L.white_MSMAll.32k_fs_LR.surf.gii
hcp_utils/data/S1200.R.flat.32k_fs_LR.surf.gii
hcp_utils/data/S1200.R.inflated_MSMAll.32k_fs_LR.surf.gii
hcp_utils/data/S1200.R.midthickness_MSMAll.32k_fs_LR.surf.gii
hcp_utils/data/S1200.R.pial_MSMAll.32k_fs_LR.surf.gii
hcp_utils/data/S1200.R.sphere.32k_fs_LR.surf.gii
hcp_utils/data/S1200.R.very_inflated_MSMAll.32k_fs_LR.surf.gii
hcp_utils/data/S1200.R.white_MSMAll.32k_fs_LR.surf.gii
hcp_utils/data/S1200.sulc_MSMAll.32k_fs_LR.dscalar.nii
hcp_utils/data/ca_network_1.1.npz
hcp_utils/data/ca_parcels_1.1.npz
hcp_utils/data/cortical_adjacency.npz
hcp_utils/data/fMRI_vertex_info_32k.npz
hcp_utils/data/mmp_1.0.npz
hcp_utils/data/standard.npz
hcp_utils/data/yeo17.npz
hcp_utils/data/yeo7.npz
hcp_utils-0.1.0.dist-info/LICENSE
hcp_utils-0.1.0.dist-info/METADATA
hcp_utils-0.1.0.dist-info/WHEEL
hcp_utils-0.1.0.dist-info/top_level.txt
hcp_utils-0.1.0.dist-info/RECORD
