Metadata-Version: 2.1
Name: hcp-utils
Version: 0.1.0
Summary: A set of utilities for working with HCP-style fMRI data with nilearn.
Home-page: https://github.com/rmldj/hcp-utils
Author: Romuald A. Janik
Author-email: romuald.janik@gmail.com
License: UNKNOWN
Platform: UNKNOWN
Classifier: Programming Language :: Python :: 3
Classifier: License :: OSI Approved :: MIT License
Classifier: Operating System :: OS Independent
Requires-Python: >=3.6
